stadtreinigung_hamburg/GarbageCollection.py
stadtreinigung_hamburg/StadtreinigungHamburg.py
stadtreinigung_hamburg/__init__.py
stadtreinigung_hamburg/__main__.py
stadtreinigung_hamburg/stadtreinigung_hamburg.py
stadtreinigung_hamburg-0.3.3.dist-info/licenses/LICENSE
stadtreinigung_hamburg-0.3.3.dist-info/METADATA
stadtreinigung_hamburg-0.3.3.dist-info/WHEEL
stadtreinigung_hamburg-0.3.3.dist-info/entry_points.txt
stadtreinigung_hamburg-0.3.3.dist-info/top_level.txt
stadtreinigung_hamburg-0.3.3.dist-info/RECORD
