Metadata-Version: 2.4
Name: stadtreinigung_hamburg
Version: 0.3.3
Summary: A library to get garbage collection dates in Hamburg.
Home-page: https://github.com/vigonotion/stadtreinigung_hamburg
Author: Tom Schneider
Author-email: Tom Schneider <tom@sutomaji.net>
License: MIT
Project-URL: Homepage, https://github.com/vigonotion/stadtreinigung_hamburg
Classifier: License :: OSI Approved :: MIT License
Classifier: Programming Language :: Python
Classifier: Programming Language :: Python :: 3
Classifier: Programming Language :: Python :: 3.6
Classifier: Programming Language :: Python :: Implementation :: CPython
Classifier: Programming Language :: Python :: Implementation :: PyPy
Requires-Python: >=3.6.0
License-File: LICENSE
Requires-Dist: requests_html
Requires-Dist: argparse
Requires-Dist: lxml-html-clean>=0.4.2
Requires-Dist: python-dateutil>=2.9.0.post0
Dynamic: author
Dynamic: home-page
Dynamic: license-file
Dynamic: requires-python
